Metadata-Version: 2.4
Name: llm-tools-sqlite
Version: 0.1
Summary: LLM tools for running queries against SQLite
Author: Simon Willison
License-Expression: Apache-2.0
Project-URL: Homepage, https://github.com/simonw/llm-tools-sqlite
Project-URL: Changelog, https://github.com/simonw/llm-tools-sqlite/releases
Project-URL: Issues, https://github.com/simonw/llm-tools-sqlite/issues
Project-URL: CI, https://github.com/simonw/llm-tools-sqlite/actions
Requires-Python: >=3.9
License-File: LICENSE
Requires-Dist: llm>=0.26
Provides-Extra: test
Requires-Dist: pytest; extra == "test"
Requires-Dist: llm-echo>=0.3a1; extra == "test"
Dynamic: license-file
